netsplit/__init__.py
netsplit/cli.py
netsplit-0.3.6.dist-info/LICENSE
netsplit-0.3.6.dist-info/METADATA
netsplit-0.3.6.dist-info/WHEEL
netsplit-0.3.6.dist-info/entry_points.txt
netsplit-0.3.6.dist-info/RECORD
