Metadata-Version: 2.3
Name: netsplit
Version: 0.3.6
Summary: Netsplit can help slice and dice your IP space
Author: Nikos Chasiotis
Author-email: hasiotis@gmail.com
Requires-Python: >=3.10,<4.0
Classifier: Programming Language :: Python :: 3
Classifier: Programming Language :: Python :: 3.10
Classifier: Programming Language :: Python :: 3.11
Classifier: Programming Language :: Python :: 3.12
Classifier: Programming Language :: Python :: 3.13
Requires-Dist: click (>=8.0,<9.0)
Requires-Dist: ipaddress (>=1.0.23,<2.0.0)
Requires-Dist: rich (>=13.7.0,<14.0.0)
Requires-Dist: tomli (>=2.0.1,<3.0.0)
